mogilefs_explorer/__init__.py
django_mogilefs_explorer-0.1.dist-info/LICENSE
django_mogilefs_explorer-0.1.dist-info/METADATA
django_mogilefs_explorer-0.1.dist-info/WHEEL
django_mogilefs_explorer-0.1.dist-info/top_level.txt
django_mogilefs_explorer-0.1.dist-info/RECORD
