Metadata-Version: 2.1
Name: django-mogilefs-explorer
Version: 0.1
Summary: Django admin helper application to manage MogileFS installation.
Home-page: https://github.com/vicpopov/django-mogilefs-explorer
Author: Victor Popov
Author-email: v.a.popov@gmail.com
License: Apache
Platform: UNKNOWN
Classifier: Development Status :: 1 - Planning
Classifier: Environment :: Web Environment
Classifier: Framework :: Django
Classifier: Framework :: Django :: 1.11
Classifier: Framework :: Django :: 2.0
Classifier: Framework :: Django :: 2.1
Classifier: Intended Audience :: Developers
Classifier: Intended Audience :: System Administrators
Classifier: License :: OSI Approved :: Apache Software License
Classifier: Operating System :: OS Independent
Classifier: Programming Language :: Python
Classifier: Programming Language :: Python :: 3
Classifier: Programming Language :: Python :: Implementation :: CPython
Requires-Python: >=3.5.0
